openeditor/__init__.py
openeditor/lib.py
openeditor-0.3.1.dist-info/LICENSE
openeditor-0.3.1.dist-info/WHEEL
openeditor-0.3.1.dist-info/METADATA
openeditor-0.3.1.dist-info/RECORD
