Metadata-Version: 2.1
Name: openeditor
Version: 0.3.1
Summary: Edit files with your $EDITOR, like git commit does.
Home-page: https://github.com/metov/openeditor
License: MIT
Author: Azat Akhmetov
Requires-Python: >=3.6,<4.0
Classifier: License :: OSI Approved :: MIT License
Classifier: Programming Language :: Python :: 3
Classifier: Programming Language :: Python :: 3.6
Classifier: Programming Language :: Python :: 3.7
Classifier: Programming Language :: Python :: 3.8
Classifier: Programming Language :: Python :: 3.9
Project-URL: Repository, https://github.com/metov/openeditor
